[
  {
    "name": "Joram",
    "id": 1,
    "days":
    {
      "day":
              [
                {"dayNumber": 1, "typeOfLeave": "atv"},
                {"dayNumber": 2, "typeOfLeave": "vrij"},
                {"dayNumber": 3, "typeOfLeave": "vrij"},
                {"dayNumber": 15, "typeOfLeave": "atv"}
              ]
    }
  },
  {
    "name": "Eline",
    "id": 2,
    "days":
    {
      "day":
      [
        {"dayNumber": 14, "typeOfLeave": "atv"},
        {"dayNumber": 15, "typeOfLeave": "vrij"},
        {"dayNumber": 16, "typeOfLeave": "vrij"},
        {"dayNumber": 28, "typeOfLeave": "atv"}
      ]
    }
  },
  {
    "name": "Marlies",
    "id": 3,
    "days":
    {
      "day":
      [
        {"dayNumber": 11, "typeOfLeave": "atv"},
        {"dayNumber": 15, "typeOfLeave": "z"},
        {"dayNumber": 16, "typeOfLeave": "z"},
        {"dayNumber": 25, "typeOfLeave": "atv"}
      ]
    }
  },
  {
    "name": "Melvin",
    "id": 4,
    "days":
    {
      "day":
      [
        {"dayNumber": 11, "typeOfLeave": "atv"},
        {"dayNumber": 15, "typeOfLeave": "vrij"},
        {"dayNumber": 16, "typeOfLeave": "vrij"},
        {"dayNumber": 25, "typeOfLeave": "atv"}
      ]
    }
  },
  {
    "name": "Kathy",
    "id": 5,
    "days":
    {
      "day":
      [
        {"dayNumber": 11, "typeOfLeave": "vrij"},
        {"dayNumber": 15, "typeOfLeave": "vrij"},
        {"dayNumber": 16, "typeOfLeave": "vrij"},
        {"dayNumber": 25, "typeOfLeave": "atv"}
      ]
    }
  },
  {
    "name": "TEST",
    "id": 6,
    "days":
    {
      "day":
      [
        {"dayNumber": 4, "typeOfLeave": "vrij"},
        {"dayNumber": 14, "typeOfLeave": "vrij"},
        {"dayNumber": 17, "typeOfLeave": "vrij"},
        {"dayNumber": 27, "typeOfLeave": "atv"}
      ]
    }
  }

]
